{
  "unversionedId": "Algorithm/Acwing算法基础课/ch3/readme",
  "id": "Algorithm/Acwing算法基础课/ch3/readme",
  "title": "Chapter3 Search and Graph",
  "description": "DFS",
  "source": "@site/docs\\Algorithm\\01.Acwing算法基础课\\ch3\\readme.md",
  "sourceDirName": "Algorithm/01.Acwing算法基础课/ch3",
  "slug": "/Algorithm/Acwing算法基础课/ch3/",
  "permalink": "/docs/Algorithm/Acwing算法基础课/ch3/",
  "editUrl": "https://github.com/PommesPeter/memo.pommespeter.space/docs/Algorithm/01.Acwing算法基础课/ch3/readme.md",
  "tags": [],
  "version": "current",
  "frontMatter": {},
  "sidebar": "Algorithm",
  "previous": {
    "title": "闫式DP分析法",
    "permalink": "/docs/Algorithm/Acwing算法基础课/ch5/闫式dp分析"
  },
  "next": {
    "title": "第十二届蓝桥杯省赛第二场-2021.5.9",
    "permalink": "/docs/Algorithm/蓝桥杯历年真题/第十二届蓝桥杯省赛第二场_2021_5_9/第十二届蓝桥杯省赛第二场(2021.5.9)"
  }
}