{
  "pluginId": "default",
  "version": "current",
  "label": "Next",
  "banner": null,
  "badge": false,
  "className": "docs-version-current",
  "isLast": true,
  "docsSidebars": {
    "tutorialSidebar": [
      {
        "type": "link",
        "label": "Tutorial Intro",
        "href": "/docs/intro",
        "docId": "intro"
      },
      {
        "type": "category",
        "label": "Tutorial - Basics",
        "collapsible": true,
        "collapsed": true,
        "items": [
          {
            "type": "link",
            "label": "Create a Page",
            "href": "/docs/tutorial-basics/create-a-page",
            "docId": "tutorial-basics/create-a-page"
          },
          {
            "type": "link",
            "label": "Create a Document",
            "href": "/docs/tutorial-basics/create-a-document",
            "docId": "tutorial-basics/create-a-document"
          },
          {
            "type": "link",
            "label": "Create a Blog Post",
            "href": "/docs/tutorial-basics/create-a-blog-post",
            "docId": "tutorial-basics/create-a-blog-post"
          },
          {
            "type": "link",
            "label": "Markdown Features",
            "href": "/docs/tutorial-basics/markdown-features",
            "docId": "tutorial-basics/markdown-features"
          },
          {
            "type": "link",
            "label": "Deploy your site",
            "href": "/docs/tutorial-basics/deploy-your-site",
            "docId": "tutorial-basics/deploy-your-site"
          },
          {
            "type": "link",
            "label": "Congratulations!",
            "href": "/docs/tutorial-basics/congratulations",
            "docId": "tutorial-basics/congratulations"
          }
        ]
      },
      {
        "type": "category",
        "label": "Tutorial - Extras",
        "collapsible": true,
        "collapsed": true,
        "items": [
          {
            "type": "link",
            "label": "Manage Docs Versions",
            "href": "/docs/tutorial-extras/manage-docs-versions",
            "docId": "tutorial-extras/manage-docs-versions"
          },
          {
            "type": "link",
            "label": "Translate your site",
            "href": "/docs/tutorial-extras/translate-your-site",
            "docId": "tutorial-extras/translate-your-site"
          }
        ]
      },
      {
        "type": "category",
        "label": "Courses",
        "collapsible": true,
        "collapsed": true,
        "items": [
          {
            "type": "category",
            "label": "面向对象程序设计",
            "collapsible": true,
            "collapsed": true,
            "items": [
              {
                "type": "link",
                "label": "Java 类",
                "href": "/docs/Courses/面向对象程序设计/类-继承-多态",
                "docId": "Courses/面向对象程序设计/类-继承-多态"
              },
              {
                "type": "link",
                "label": "Java GUI编程",
                "href": "/docs/Courses/面向对象程序设计/Java-Gui编程",
                "docId": "Courses/面向对象程序设计/Java-Gui编程"
              },
              {
                "type": "link",
                "label": "Java 基本概念",
                "href": "/docs/Courses/面向对象程序设计/基础概念",
                "docId": "Courses/面向对象程序设计/基础概念"
              },
              {
                "type": "link",
                "label": "Java 实用类大全",
                "href": "/docs/Courses/面向对象程序设计/实用类大全",
                "docId": "Courses/面向对象程序设计/实用类大全"
              },
              {
                "type": "link",
                "label": "Java 多线程与网络",
                "href": "/docs/Courses/面向对象程序设计/多线程与网络",
                "docId": "Courses/面向对象程序设计/多线程与网络"
              }
            ]
          },
          {
            "type": "category",
            "label": "数学建模",
            "collapsible": true,
            "collapsed": true,
            "items": [
              {
                "type": "link",
                "label": "线性规划算法",
                "href": "/docs/Courses/数学建模/线性规划",
                "docId": "Courses/数学建模/线性规划"
              },
              {
                "type": "link",
                "label": "非线性规划算法",
                "href": "/docs/Courses/数学建模/非线性规划",
                "docId": "Courses/数学建模/非线性规划"
              },
              {
                "type": "link",
                "label": "图优化算法",
                "href": "/docs/Courses/数学建模/图优化",
                "docId": "Courses/数学建模/图优化"
              },
              {
                "type": "link",
                "label": "微分与差分方程",
                "href": "/docs/Courses/数学建模/微分与差分",
                "docId": "Courses/数学建模/微分与差分"
              },
              {
                "type": "link",
                "label": "插值与拟合",
                "href": "/docs/Courses/数学建模/插值与拟合",
                "docId": "Courses/数学建模/插值与拟合"
              }
            ]
          },
          {
            "type": "category",
            "label": "数据库原理",
            "collapsible": true,
            "collapsed": true,
            "items": [
              {
                "type": "link",
                "label": "数据库基本概念",
                "href": "/docs/Courses/数据库原理/基本概念",
                "docId": "Courses/数据库原理/基本概念"
              },
              {
                "type": "link",
                "label": "关系代数和SQL",
                "href": "/docs/Courses/数据库原理/关系代数与SQL",
                "docId": "Courses/数据库原理/关系代数与SQL"
              },
              {
                "type": "link",
                "label": "数据库规范性理论",
                "href": "/docs/Courses/数据库原理/数据库规范性理论",
                "docId": "Courses/数据库原理/数据库规范性理论"
              },
              {
                "type": "link",
                "label": "数据库设计",
                "href": "/docs/Courses/数据库原理/数据库设计",
                "docId": "Courses/数据库原理/数据库设计"
              },
              {
                "type": "link",
                "label": "数据库恢复",
                "href": "/docs/Courses/数据库原理/数据库恢复",
                "docId": "Courses/数据库原理/数据库恢复"
              },
              {
                "type": "link",
                "label": "数据库安全性",
                "href": "/docs/Courses/数据库原理/数据库安全",
                "docId": "Courses/数据库原理/数据库安全"
              },
              {
                "type": "link",
                "label": "数据库并发",
                "href": "/docs/Courses/数据库原理/数据库并发",
                "docId": "Courses/数据库原理/数据库并发"
              }
            ]
          },
          {
            "type": "category",
            "label": "算法设计与分析",
            "collapsible": true,
            "collapsed": true,
            "items": [
              {
                "type": "link",
                "label": "算法基本概念",
                "href": "/docs/Courses/算法设计与分析/基本概念",
                "docId": "Courses/算法设计与分析/基本概念"
              },
              {
                "type": "link",
                "label": "分治算法",
                "href": "/docs/Courses/算法设计与分析/分治算法",
                "docId": "Courses/算法设计与分析/分治算法"
              },
              {
                "type": "link",
                "label": "动态规划",
                "href": "/docs/Courses/算法设计与分析/动态规划",
                "docId": "Courses/算法设计与分析/动态规划"
              },
              {
                "type": "link",
                "label": "贪心算法",
                "href": "/docs/Courses/算法设计与分析/贪心算法",
                "docId": "Courses/算法设计与分析/贪心算法"
              },
              {
                "type": "link",
                "label": "回溯算法",
                "href": "/docs/Courses/算法设计与分析/回溯算法",
                "docId": "Courses/算法设计与分析/回溯算法"
              }
            ]
          },
          {
            "type": "category",
            "label": "操作系统",
            "collapsible": true,
            "collapsed": true,
            "items": [
              {
                "type": "link",
                "label": "操作系统基础概念",
                "href": "/docs/Courses/操作系统/操作系统基础概念",
                "docId": "Courses/操作系统/操作系统基础概念"
              },
              {
                "type": "link",
                "label": "进程与线程",
                "href": "/docs/Courses/操作系统/进程与线程",
                "docId": "Courses/操作系统/进程与线程"
              },
              {
                "type": "link",
                "label": "内存管理",
                "href": "/docs/Courses/操作系统/内存管理",
                "docId": "Courses/操作系统/内存管理"
              },
              {
                "type": "link",
                "label": "文件系统",
                "href": "/docs/Courses/操作系统/文件系统",
                "docId": "Courses/操作系统/文件系统"
              },
              {
                "type": "link",
                "label": "IO设备管理",
                "href": "/docs/Courses/操作系统/IO设备管理",
                "docId": "Courses/操作系统/IO设备管理"
              },
              {
                "type": "link",
                "label": "并行程序设计",
                "href": "/docs/Courses/操作系统/并行程序设计",
                "docId": "Courses/操作系统/并行程序设计"
              }
            ]
          },
          {
            "type": "category",
            "label": "大数据分析和原理",
            "collapsible": true,
            "collapsed": true,
            "items": [
              {
                "type": "link",
                "label": "大数据概述",
                "href": "/docs/Courses/大数据分析和原理/大数据概述",
                "docId": "Courses/大数据分析和原理/大数据概述"
              },
              {
                "type": "link",
                "label": "Hadoop技术原理",
                "href": "/docs/Courses/大数据分析和原理/Hadoop技术原理",
                "docId": "Courses/大数据分析和原理/Hadoop技术原理"
              },
              {
                "type": "link",
                "label": "HDFS技术原理",
                "href": "/docs/Courses/大数据分析和原理/HDFS技术原理",
                "docId": "Courses/大数据分析和原理/HDFS技术原理"
              },
              {
                "type": "link",
                "label": "HBase技术原理",
                "href": "/docs/Courses/大数据分析和原理/HBase技术原理",
                "docId": "Courses/大数据分析和原理/HBase技术原理"
              },
              {
                "type": "link",
                "label": "NoSQL相关概念",
                "href": "/docs/Courses/大数据分析和原理/NoSQL概念",
                "docId": "Courses/大数据分析和原理/NoSQL概念"
              },
              {
                "type": "link",
                "label": "NoSQL相关概念",
                "href": "/docs/Courses/大数据分析和原理/MapReduce技术原理",
                "docId": "Courses/大数据分析和原理/MapReduce技术原理"
              },
              {
                "type": "link",
                "label": "NoSQL相关概念",
                "href": "/docs/Courses/大数据分析和原理/Spark技术原理",
                "docId": "Courses/大数据分析和原理/Spark技术原理"
              },
              {
                "type": "link",
                "label": "NoSQL相关概念",
                "href": "/docs/Courses/大数据分析和原理/Storm技术原理",
                "docId": "Courses/大数据分析和原理/Storm技术原理"
              }
            ]
          }
        ]
      },
      {
        "type": "category",
        "label": "DeepLearning",
        "collapsible": true,
        "collapsed": true,
        "items": [
          {
            "type": "category",
            "label": "科研方法",
            "collapsible": true,
            "collapsed": true,
            "items": [
              {
                "type": "link",
                "label": "如何读一篇论文",
                "href": "/docs/DeepLearning/科研方法/如何读论文",
                "docId": "DeepLearning/科研方法/如何读论文"
              }
            ]
          },
          {
            "type": "category",
            "label": "深度学习导论",
            "collapsible": true,
            "collapsed": true,
            "items": [
              {
                "type": "link",
                "label": "神经网络算法解析",
                "href": "/docs/DeepLearning/深度学习导论/神经网络算法解析",
                "docId": "DeepLearning/深度学习导论/神经网络算法解析"
              }
            ]
          },
          {
            "type": "category",
            "label": "深度学习框架",
            "collapsible": true,
            "collapsed": true,
            "items": [
              {
                "type": "category",
                "label": "mmdetection",
                "collapsible": true,
                "collapsed": true,
                "items": [
                  {
                    "type": "link",
                    "label": "MMDetection Instruction",
                    "href": "/docs/DeepLearning/深度学习框架/mmdetection/Instruction",
                    "docId": "DeepLearning/深度学习框架/mmdetection/Instruction"
                  },
                  {
                    "type": "link",
                    "label": "MMDetection Installation",
                    "href": "/docs/DeepLearning/深度学习框架/mmdetection/Installation Tutorial",
                    "docId": "DeepLearning/深度学习框架/mmdetection/Installation Tutorial"
                  },
                  {
                    "type": "link",
                    "label": "How to build a model with config file by yourself",
                    "href": "/docs/DeepLearning/深度学习框架/mmdetection/How to builld a model with configs by yourself",
                    "docId": "DeepLearning/深度学习框架/mmdetection/How to builld a model with configs by yourself"
                  }
                ]
              }
            ]
          },
          {
            "type": "category",
            "label": "神经网络杂项",
            "collapsible": true,
            "collapsed": true,
            "items": [
              {
                "type": "link",
                "label": "反卷积与棋盘效应",
                "href": "/docs/DeepLearning/神经网络杂项/反卷积与棋盘效应",
                "docId": "DeepLearning/神经网络杂项/反卷积与棋盘效应"
              }
            ]
          },
          {
            "type": "category",
            "label": "目标检测",
            "collapsible": true,
            "collapsed": true,
            "items": [
              {
                "type": "link",
                "label": "yaml改进",
                "href": "/docs/DeepLearning/目标检测/yaml改进",
                "docId": "DeepLearning/目标检测/yaml改进"
              },
              {
                "type": "link",
                "label": "yolov5",
                "href": "/docs/DeepLearning/目标检测/yolov5介绍",
                "docId": "DeepLearning/目标检测/yolov5介绍"
              }
            ]
          }
        ]
      },
      {
        "type": "category",
        "label": "Algorithm",
        "collapsible": true,
        "collapsed": true,
        "items": [
          {
            "type": "category",
            "label": "蓝桥杯历年真题",
            "collapsible": true,
            "collapsed": true,
            "items": [
              {
                "type": "category",
                "label": "第十二届蓝桥杯省赛第二场_2021_5_9",
                "collapsible": true,
                "collapsed": true,
                "items": [
                  {
                    "type": "link",
                    "label": "第十二届蓝桥杯省赛第二场-2021.5.9",
                    "href": "/docs/Algorithm/蓝桥杯历年真题/第十二届蓝桥杯省赛第二场_2021_5_9/第十二届蓝桥杯省赛第二场(2021.5.9)",
                    "docId": "Algorithm/蓝桥杯历年真题/第十二届蓝桥杯省赛第二场_2021_5_9/第十二届蓝桥杯省赛第二场(2021.5.9)"
                  }
                ]
              }
            ]
          }
        ]
      }
    ],
    "Courses": [
      {
        "type": "category",
        "label": "面向对象程序设计",
        "collapsible": true,
        "collapsed": true,
        "items": [
          {
            "type": "link",
            "label": "Java 类",
            "href": "/docs/Courses/面向对象程序设计/类-继承-多态",
            "docId": "Courses/面向对象程序设计/类-继承-多态"
          },
          {
            "type": "link",
            "label": "Java GUI编程",
            "href": "/docs/Courses/面向对象程序设计/Java-Gui编程",
            "docId": "Courses/面向对象程序设计/Java-Gui编程"
          },
          {
            "type": "link",
            "label": "Java 基本概念",
            "href": "/docs/Courses/面向对象程序设计/基础概念",
            "docId": "Courses/面向对象程序设计/基础概念"
          },
          {
            "type": "link",
            "label": "Java 实用类大全",
            "href": "/docs/Courses/面向对象程序设计/实用类大全",
            "docId": "Courses/面向对象程序设计/实用类大全"
          },
          {
            "type": "link",
            "label": "Java 多线程与网络",
            "href": "/docs/Courses/面向对象程序设计/多线程与网络",
            "docId": "Courses/面向对象程序设计/多线程与网络"
          }
        ]
      },
      {
        "type": "category",
        "label": "数学建模",
        "collapsible": true,
        "collapsed": true,
        "items": [
          {
            "type": "link",
            "label": "线性规划算法",
            "href": "/docs/Courses/数学建模/线性规划",
            "docId": "Courses/数学建模/线性规划"
          },
          {
            "type": "link",
            "label": "非线性规划算法",
            "href": "/docs/Courses/数学建模/非线性规划",
            "docId": "Courses/数学建模/非线性规划"
          },
          {
            "type": "link",
            "label": "图优化算法",
            "href": "/docs/Courses/数学建模/图优化",
            "docId": "Courses/数学建模/图优化"
          },
          {
            "type": "link",
            "label": "微分与差分方程",
            "href": "/docs/Courses/数学建模/微分与差分",
            "docId": "Courses/数学建模/微分与差分"
          },
          {
            "type": "link",
            "label": "插值与拟合",
            "href": "/docs/Courses/数学建模/插值与拟合",
            "docId": "Courses/数学建模/插值与拟合"
          }
        ]
      },
      {
        "type": "category",
        "label": "数据库原理",
        "collapsible": true,
        "collapsed": true,
        "items": [
          {
            "type": "link",
            "label": "数据库基本概念",
            "href": "/docs/Courses/数据库原理/基本概念",
            "docId": "Courses/数据库原理/基本概念"
          },
          {
            "type": "link",
            "label": "关系代数和SQL",
            "href": "/docs/Courses/数据库原理/关系代数与SQL",
            "docId": "Courses/数据库原理/关系代数与SQL"
          },
          {
            "type": "link",
            "label": "数据库规范性理论",
            "href": "/docs/Courses/数据库原理/数据库规范性理论",
            "docId": "Courses/数据库原理/数据库规范性理论"
          },
          {
            "type": "link",
            "label": "数据库设计",
            "href": "/docs/Courses/数据库原理/数据库设计",
            "docId": "Courses/数据库原理/数据库设计"
          },
          {
            "type": "link",
            "label": "数据库恢复",
            "href": "/docs/Courses/数据库原理/数据库恢复",
            "docId": "Courses/数据库原理/数据库恢复"
          },
          {
            "type": "link",
            "label": "数据库安全性",
            "href": "/docs/Courses/数据库原理/数据库安全",
            "docId": "Courses/数据库原理/数据库安全"
          },
          {
            "type": "link",
            "label": "数据库并发",
            "href": "/docs/Courses/数据库原理/数据库并发",
            "docId": "Courses/数据库原理/数据库并发"
          }
        ]
      },
      {
        "type": "category",
        "label": "算法设计与分析",
        "collapsible": true,
        "collapsed": true,
        "items": [
          {
            "type": "link",
            "label": "算法基本概念",
            "href": "/docs/Courses/算法设计与分析/基本概念",
            "docId": "Courses/算法设计与分析/基本概念"
          },
          {
            "type": "link",
            "label": "分治算法",
            "href": "/docs/Courses/算法设计与分析/分治算法",
            "docId": "Courses/算法设计与分析/分治算法"
          },
          {
            "type": "link",
            "label": "动态规划",
            "href": "/docs/Courses/算法设计与分析/动态规划",
            "docId": "Courses/算法设计与分析/动态规划"
          },
          {
            "type": "link",
            "label": "贪心算法",
            "href": "/docs/Courses/算法设计与分析/贪心算法",
            "docId": "Courses/算法设计与分析/贪心算法"
          },
          {
            "type": "link",
            "label": "回溯算法",
            "href": "/docs/Courses/算法设计与分析/回溯算法",
            "docId": "Courses/算法设计与分析/回溯算法"
          }
        ]
      },
      {
        "type": "category",
        "label": "操作系统",
        "collapsible": true,
        "collapsed": true,
        "items": [
          {
            "type": "link",
            "label": "操作系统基础概念",
            "href": "/docs/Courses/操作系统/操作系统基础概念",
            "docId": "Courses/操作系统/操作系统基础概念"
          },
          {
            "type": "link",
            "label": "进程与线程",
            "href": "/docs/Courses/操作系统/进程与线程",
            "docId": "Courses/操作系统/进程与线程"
          },
          {
            "type": "link",
            "label": "内存管理",
            "href": "/docs/Courses/操作系统/内存管理",
            "docId": "Courses/操作系统/内存管理"
          },
          {
            "type": "link",
            "label": "文件系统",
            "href": "/docs/Courses/操作系统/文件系统",
            "docId": "Courses/操作系统/文件系统"
          },
          {
            "type": "link",
            "label": "IO设备管理",
            "href": "/docs/Courses/操作系统/IO设备管理",
            "docId": "Courses/操作系统/IO设备管理"
          },
          {
            "type": "link",
            "label": "并行程序设计",
            "href": "/docs/Courses/操作系统/并行程序设计",
            "docId": "Courses/操作系统/并行程序设计"
          }
        ]
      },
      {
        "type": "category",
        "label": "大数据分析和原理",
        "collapsible": true,
        "collapsed": true,
        "items": [
          {
            "type": "link",
            "label": "大数据概述",
            "href": "/docs/Courses/大数据分析和原理/大数据概述",
            "docId": "Courses/大数据分析和原理/大数据概述"
          },
          {
            "type": "link",
            "label": "Hadoop技术原理",
            "href": "/docs/Courses/大数据分析和原理/Hadoop技术原理",
            "docId": "Courses/大数据分析和原理/Hadoop技术原理"
          },
          {
            "type": "link",
            "label": "HDFS技术原理",
            "href": "/docs/Courses/大数据分析和原理/HDFS技术原理",
            "docId": "Courses/大数据分析和原理/HDFS技术原理"
          },
          {
            "type": "link",
            "label": "HBase技术原理",
            "href": "/docs/Courses/大数据分析和原理/HBase技术原理",
            "docId": "Courses/大数据分析和原理/HBase技术原理"
          },
          {
            "type": "link",
            "label": "NoSQL相关概念",
            "href": "/docs/Courses/大数据分析和原理/NoSQL概念",
            "docId": "Courses/大数据分析和原理/NoSQL概念"
          },
          {
            "type": "link",
            "label": "NoSQL相关概念",
            "href": "/docs/Courses/大数据分析和原理/MapReduce技术原理",
            "docId": "Courses/大数据分析和原理/MapReduce技术原理"
          },
          {
            "type": "link",
            "label": "NoSQL相关概念",
            "href": "/docs/Courses/大数据分析和原理/Spark技术原理",
            "docId": "Courses/大数据分析和原理/Spark技术原理"
          },
          {
            "type": "link",
            "label": "NoSQL相关概念",
            "href": "/docs/Courses/大数据分析和原理/Storm技术原理",
            "docId": "Courses/大数据分析和原理/Storm技术原理"
          }
        ]
      }
    ],
    "DeepLearning": [
      {
        "type": "category",
        "label": "科研方法",
        "collapsible": true,
        "collapsed": true,
        "items": [
          {
            "type": "link",
            "label": "如何读一篇论文",
            "href": "/docs/DeepLearning/科研方法/如何读论文",
            "docId": "DeepLearning/科研方法/如何读论文"
          }
        ]
      },
      {
        "type": "category",
        "label": "深度学习导论",
        "collapsible": true,
        "collapsed": true,
        "items": [
          {
            "type": "link",
            "label": "神经网络算法解析",
            "href": "/docs/DeepLearning/深度学习导论/神经网络算法解析",
            "docId": "DeepLearning/深度学习导论/神经网络算法解析"
          }
        ]
      },
      {
        "type": "category",
        "label": "深度学习框架",
        "collapsible": true,
        "collapsed": true,
        "items": [
          {
            "type": "category",
            "label": "mmdetection",
            "collapsible": true,
            "collapsed": true,
            "items": [
              {
                "type": "link",
                "label": "MMDetection Instruction",
                "href": "/docs/DeepLearning/深度学习框架/mmdetection/Instruction",
                "docId": "DeepLearning/深度学习框架/mmdetection/Instruction"
              },
              {
                "type": "link",
                "label": "MMDetection Installation",
                "href": "/docs/DeepLearning/深度学习框架/mmdetection/Installation Tutorial",
                "docId": "DeepLearning/深度学习框架/mmdetection/Installation Tutorial"
              },
              {
                "type": "link",
                "label": "How to build a model with config file by yourself",
                "href": "/docs/DeepLearning/深度学习框架/mmdetection/How to builld a model with configs by yourself",
                "docId": "DeepLearning/深度学习框架/mmdetection/How to builld a model with configs by yourself"
              }
            ]
          }
        ]
      },
      {
        "type": "category",
        "label": "神经网络杂项",
        "collapsible": true,
        "collapsed": true,
        "items": [
          {
            "type": "link",
            "label": "反卷积与棋盘效应",
            "href": "/docs/DeepLearning/神经网络杂项/反卷积与棋盘效应",
            "docId": "DeepLearning/神经网络杂项/反卷积与棋盘效应"
          }
        ]
      },
      {
        "type": "category",
        "label": "目标检测",
        "collapsible": true,
        "collapsed": true,
        "items": [
          {
            "type": "link",
            "label": "yaml改进",
            "href": "/docs/DeepLearning/目标检测/yaml改进",
            "docId": "DeepLearning/目标检测/yaml改进"
          },
          {
            "type": "link",
            "label": "yolov5",
            "href": "/docs/DeepLearning/目标检测/yolov5介绍",
            "docId": "DeepLearning/目标检测/yolov5介绍"
          }
        ]
      }
    ],
    "Algorithm": [
      {
        "type": "category",
        "label": "蓝桥杯历年真题",
        "collapsible": true,
        "collapsed": true,
        "items": [
          {
            "type": "category",
            "label": "第十二届蓝桥杯省赛第二场_2021_5_9",
            "collapsible": true,
            "collapsed": true,
            "items": [
              {
                "type": "link",
                "label": "第十二届蓝桥杯省赛第二场-2021.5.9",
                "href": "/docs/Algorithm/蓝桥杯历年真题/第十二届蓝桥杯省赛第二场_2021_5_9/第十二届蓝桥杯省赛第二场(2021.5.9)",
                "docId": "Algorithm/蓝桥杯历年真题/第十二届蓝桥杯省赛第二场_2021_5_9/第十二届蓝桥杯省赛第二场(2021.5.9)"
              }
            ]
          }
        ]
      }
    ]
  },
  "docs": {
    "Algorithm/蓝桥杯历年真题/第十二届蓝桥杯省赛第二场_2021_5_9/第十二届蓝桥杯省赛第二场(2021.5.9)": {
      "id": "Algorithm/蓝桥杯历年真题/第十二届蓝桥杯省赛第二场_2021_5_9/第十二届蓝桥杯省赛第二场(2021.5.9)",
      "title": "第十二届蓝桥杯省赛第二场-2021.5.9",
      "description": "题目在这",
      "sidebar": "Algorithm"
    },
    "Courses/大数据分析和原理/Hadoop技术原理": {
      "id": "Courses/大数据分析和原理/Hadoop技术原理",
      "title": "Hadoop技术原理",
      "description": "什么是 Hadoop？",
      "sidebar": "Courses"
    },
    "Courses/大数据分析和原理/HBase技术原理": {
      "id": "Courses/大数据分析和原理/HBase技术原理",
      "title": "HBase技术原理",
      "description": "HBase 数据模型",
      "sidebar": "Courses"
    },
    "Courses/大数据分析和原理/HDFS技术原理": {
      "id": "Courses/大数据分析和原理/HDFS技术原理",
      "title": "HDFS技术原理",
      "description": "什么是 HDFS？",
      "sidebar": "Courses"
    },
    "Courses/大数据分析和原理/MapReduce技术原理": {
      "id": "Courses/大数据分析和原理/MapReduce技术原理",
      "title": "NoSQL相关概念",
      "description": "Map 和 Reduce 方法",
      "sidebar": "Courses"
    },
    "Courses/大数据分析和原理/NoSQL概念": {
      "id": "Courses/大数据分析和原理/NoSQL概念",
      "title": "NoSQL相关概念",
      "description": "数据库类型",
      "sidebar": "Courses"
    },
    "Courses/大数据分析和原理/Spark技术原理": {
      "id": "Courses/大数据分析和原理/Spark技术原理",
      "title": "NoSQL相关概念",
      "description": "基本概念",
      "sidebar": "Courses"
    },
    "Courses/大数据分析和原理/Storm技术原理": {
      "id": "Courses/大数据分析和原理/Storm技术原理",
      "title": "NoSQL相关概念",
      "description": "流计算概述",
      "sidebar": "Courses"
    },
    "Courses/大数据分析和原理/大数据概述": {
      "id": "Courses/大数据分析和原理/大数据概述",
      "title": "大数据概述",
      "description": "大数据概念",
      "sidebar": "Courses"
    },
    "Courses/操作系统/IO设备管理": {
      "id": "Courses/操作系统/IO设备管理",
      "title": "IO设备管理",
      "description": "",
      "sidebar": "Courses"
    },
    "Courses/操作系统/内存管理": {
      "id": "Courses/操作系统/内存管理",
      "title": "内存管理",
      "description": "",
      "sidebar": "Courses"
    },
    "Courses/操作系统/并行程序设计": {
      "id": "Courses/操作系统/并行程序设计",
      "title": "并行程序设计",
      "description": "",
      "sidebar": "Courses"
    },
    "Courses/操作系统/操作系统基础概念": {
      "id": "Courses/操作系统/操作系统基础概念",
      "title": "操作系统基础概念",
      "description": "概念",
      "sidebar": "Courses"
    },
    "Courses/操作系统/文件系统": {
      "id": "Courses/操作系统/文件系统",
      "title": "文件系统",
      "description": "文件——就是一组有意义的信息、数据集合，但是各种文件有不同的特性，而文件的管理也是交由OS来管理",
      "sidebar": "Courses"
    },
    "Courses/操作系统/进程与线程": {
      "id": "Courses/操作系统/进程与线程",
      "title": "进程与线程",
      "description": "",
      "sidebar": "Courses"
    },
    "Courses/数学建模/图优化": {
      "id": "Courses/数学建模/图优化",
      "title": "图优化算法",
      "description": "图表示",
      "sidebar": "Courses"
    },
    "Courses/数学建模/微分与差分": {
      "id": "Courses/数学建模/微分与差分",
      "title": "微分与差分方程",
      "description": "微分",
      "sidebar": "Courses"
    },
    "Courses/数学建模/插值与拟合": {
      "id": "Courses/数学建模/插值与拟合",
      "title": "插值与拟合",
      "description": "插值",
      "sidebar": "Courses"
    },
    "Courses/数学建模/线性规划": {
      "id": "Courses/数学建模/线性规划",
      "title": "线性规划算法",
      "description": "概念",
      "sidebar": "Courses"
    },
    "Courses/数学建模/非线性规划": {
      "id": "Courses/数学建模/非线性规划",
      "title": "非线性规划算法",
      "description": "概念",
      "sidebar": "Courses"
    },
    "Courses/数据库原理/关系代数与SQL": {
      "id": "Courses/数据库原理/关系代数与SQL",
      "title": "关系代数和SQL",
      "description": "关系完整性",
      "sidebar": "Courses"
    },
    "Courses/数据库原理/基本概念": {
      "id": "Courses/数据库原理/基本概念",
      "title": "数据库基本概念",
      "description": "数据库术语",
      "sidebar": "Courses"
    },
    "Courses/数据库原理/数据库安全": {
      "id": "Courses/数据库原理/数据库安全",
      "title": "数据库安全性",
      "description": "不安全因素:",
      "sidebar": "Courses"
    },
    "Courses/数据库原理/数据库并发": {
      "id": "Courses/数据库原理/数据库并发",
      "title": "数据库并发",
      "description": "并发概念",
      "sidebar": "Courses"
    },
    "Courses/数据库原理/数据库恢复": {
      "id": "Courses/数据库原理/数据库恢复",
      "title": "数据库恢复",
      "description": "数据转储",
      "sidebar": "Courses"
    },
    "Courses/数据库原理/数据库规范性理论": {
      "id": "Courses/数据库原理/数据库规范性理论",
      "title": "数据库规范性理论",
      "description": "Armstrong公理系统",
      "sidebar": "Courses"
    },
    "Courses/数据库原理/数据库设计": {
      "id": "Courses/数据库原理/数据库设计",
      "title": "数据库设计",
      "description": "数据库概念设计",
      "sidebar": "Courses"
    },
    "Courses/算法设计与分析/分治算法": {
      "id": "Courses/算法设计与分析/分治算法",
      "title": "分治算法",
      "description": "分治算法本质上也是递归，只不过是表现得比较抽象。",
      "sidebar": "Courses"
    },
    "Courses/算法设计与分析/动态规划": {
      "id": "Courses/算法设计与分析/动态规划",
      "title": "动态规划",
      "description": "基础概念",
      "sidebar": "Courses"
    },
    "Courses/算法设计与分析/回溯算法": {
      "id": "Courses/算法设计与分析/回溯算法",
      "title": "回溯算法",
      "description": "",
      "sidebar": "Courses"
    },
    "Courses/算法设计与分析/基本概念": {
      "id": "Courses/算法设计与分析/基本概念",
      "title": "算法基本概念",
      "description": "著名的图灵奖获得者Donald E. Knuth曾经说:\"Computer science is the study of algorithm\"，也就是计算科学就是研究算法的科学。这门学科主要的学习方法是通过经典算法的学习，积累经验，触类旁通，举一反三。",
      "sidebar": "Courses"
    },
    "Courses/算法设计与分析/贪心算法": {
      "id": "Courses/算法设计与分析/贪心算法",
      "title": "贪心算法",
      "description": "贪心算法主要是在问题求解的试合，总是会做目前看来最好的选择，不考虑整体上的最优，考虑局部的最优，所以贪心算法一般情况下得到的是局部最优解，排除有概率得到最优解。",
      "sidebar": "Courses"
    },
    "Courses/面向对象程序设计/Java-Gui编程": {
      "id": "Courses/面向对象程序设计/Java-Gui编程",
      "title": "Java GUI编程",
      "description": "常用类",
      "sidebar": "Courses"
    },
    "Courses/面向对象程序设计/基础概念": {
      "id": "Courses/面向对象程序设计/基础概念",
      "title": "Java 基本概念",
      "description": "基本输入",
      "sidebar": "Courses"
    },
    "Courses/面向对象程序设计/多线程与网络": {
      "id": "Courses/面向对象程序设计/多线程与网络",
      "title": "Java 多线程与网络",
      "description": "多线程",
      "sidebar": "Courses"
    },
    "Courses/面向对象程序设计/实用类大全": {
      "id": "Courses/面向对象程序设计/实用类大全",
      "title": "Java 实用类大全",
      "description": "内部类",
      "sidebar": "Courses"
    },
    "Courses/面向对象程序设计/类-继承-多态": {
      "id": "Courses/面向对象程序设计/类-继承-多态",
      "title": "Java 类",
      "description": "类",
      "sidebar": "Courses"
    },
    "DeepLearning/深度学习导论/神经网络算法解析": {
      "id": "DeepLearning/深度学习导论/神经网络算法解析",
      "title": "神经网络算法解析",
      "description": "",
      "sidebar": "DeepLearning"
    },
    "DeepLearning/深度学习框架/mmdetection/How to builld a model with configs by yourself": {
      "id": "DeepLearning/深度学习框架/mmdetection/How to builld a model with configs by yourself",
      "title": "How to build a model with config file by yourself",
      "description": "Learn about Configs",
      "sidebar": "DeepLearning"
    },
    "DeepLearning/深度学习框架/mmdetection/Installation Tutorial": {
      "id": "DeepLearning/深度学习框架/mmdetection/Installation Tutorial",
      "title": "MMDetection Installation",
      "description": "说在前面，现在MM全系列框架仅支持在Linux或者MacOS上运行，Windows仍然处于实验阶段。",
      "sidebar": "DeepLearning"
    },
    "DeepLearning/深度学习框架/mmdetection/Instruction": {
      "id": "DeepLearning/深度学习框架/mmdetection/Instruction",
      "title": "MMDetection Instruction",
      "description": "MMDetection是一个基于PyTorch进行开发的开源的目标检测工具箱，通过这个工具箱能够让你很方便地构建出自己的目标检测算法。同时，这里有非常多开源的知名顶会算法，丰富的model zoo开源模型和算法。一般在很多深度学习算法竞赛，如阿里天池、百度、华为云等比赛上，你会发现很多TOP前几的大佬都是实用这些框架进行开发，而不会傻傻地自己写一个算法；还有科研上很多开源的科研成果代码都是使用这些开源的框架来实现的，像类似的框架还有 Detectron2, maskrcnn-benchmark 和 SimpleDet，但论使用自由度和开放性来说，还是mmdetection占优势，所以我们就一起加入到MM系列的大家族吧！",
      "sidebar": "DeepLearning"
    },
    "DeepLearning/目标检测/yaml改进": {
      "id": "DeepLearning/目标检测/yaml改进",
      "title": "yaml改进",
      "description": "添加了GhostBottleneck的网络结构",
      "sidebar": "DeepLearning"
    },
    "DeepLearning/目标检测/yolov5介绍": {
      "id": "DeepLearning/目标检测/yolov5介绍",
      "title": "yolov5",
      "description": "yolov5拥有强大的效果，但是在其实现强大效果的同时，其完备的封装及复杂的参数使得我们难以对其结构进行深入分析",
      "sidebar": "DeepLearning"
    },
    "DeepLearning/神经网络杂项/反卷积与棋盘效应": {
      "id": "DeepLearning/神经网络杂项/反卷积与棋盘效应",
      "title": "反卷积与棋盘效应",
      "description": "Augustus Odena，Vincent Dumoulin，Chris Olah",
      "sidebar": "DeepLearning"
    },
    "DeepLearning/科研方法/如何读论文": {
      "id": "DeepLearning/科研方法/如何读论文",
      "title": "如何读一篇论文",
      "description": "当你阅读一篇研究论文时，你的目标是了解作者的科学贡献。这不是一项容易的任务。这可能需要把这篇论文看好几遍。准备花几个小时读一篇论文。",
      "sidebar": "DeepLearning"
    },
    "intro": {
      "id": "intro",
      "title": "Tutorial Intro",
      "description": "Let's discover Docusaurus in less than 5 minutes.",
      "sidebar": "tutorialSidebar"
    },
    "tutorial-basics/congratulations": {
      "id": "tutorial-basics/congratulations",
      "title": "Congratulations!",
      "description": "You have just learned the basics of Docusaurus and made some changes to the initial template.",
      "sidebar": "tutorialSidebar"
    },
    "tutorial-basics/create-a-blog-post": {
      "id": "tutorial-basics/create-a-blog-post",
      "title": "Create a Blog Post",
      "description": "Docusaurus creates a page for each blog post, but also a blog index page, a tag system, an RSS feed...",
      "sidebar": "tutorialSidebar"
    },
    "tutorial-basics/create-a-document": {
      "id": "tutorial-basics/create-a-document",
      "title": "Create a Document",
      "description": "Documents are groups of pages connected through:",
      "sidebar": "tutorialSidebar"
    },
    "tutorial-basics/create-a-page": {
      "id": "tutorial-basics/create-a-page",
      "title": "Create a Page",
      "description": "Add Markdown or React files to src/pages to create a standalone page:",
      "sidebar": "tutorialSidebar"
    },
    "tutorial-basics/deploy-your-site": {
      "id": "tutorial-basics/deploy-your-site",
      "title": "Deploy your site",
      "description": "Docusaurus is a static-site-generator (also called Jamstack).",
      "sidebar": "tutorialSidebar"
    },
    "tutorial-basics/markdown-features": {
      "id": "tutorial-basics/markdown-features",
      "title": "Markdown Features",
      "description": "Docusaurus supports Markdown and a few additional features.",
      "sidebar": "tutorialSidebar"
    },
    "tutorial-extras/manage-docs-versions": {
      "id": "tutorial-extras/manage-docs-versions",
      "title": "Manage Docs Versions",
      "description": "Docusaurus can manage multiple versions of your docs.",
      "sidebar": "tutorialSidebar"
    },
    "tutorial-extras/translate-your-site": {
      "id": "tutorial-extras/translate-your-site",
      "title": "Translate your site",
      "description": "Let's translate docs/intro.md to French.",
      "sidebar": "tutorialSidebar"
    }
  }
}